keylin/__init__.py
keylin/api_key_auth.py
keylin/apikey_manager.py
keylin/auth.py
keylin/config.py
keylin/db.py
keylin/keylin_utils.py
keylin/models.py
keylin/schemas.py
keylin-0.7.7.dist-info/METADATA
keylin-0.7.7.dist-info/WHEEL
keylin-0.7.7.dist-info/licenses/LICENSE
keylin-0.7.7.dist-info/RECORD
