Metadata-Version: 2.4
Name: keylin
Version: 0.7.7
Summary: User model and schema library for authentication services
Project-URL: Homepage, https://github.com/beanone/keylin.git
Project-URL: Repository, https://github.com/beanone/keylin.git
Author-email: Your Name <your.email@example.com>
License-Expression: MIT
License-File: LICENSE
Classifier: Development Status :: 3 - Alpha
Classifier: Intended Audience :: Developers
Classifier: License :: OSI Approved :: MIT License
Classifier: Programming Language :: Python :: 3.12
Classifier: Topic :: Security
Classifier: Topic :: Software Development :: Libraries :: Python Modules
Requires-Python: >=3.7
Requires-Dist: aiosqlite
Requires-Dist: fastapi
Requires-Dist: fastapi-users[sqlalchemy]
Requires-Dist: pydantic-settings
Requires-Dist: sqlalchemy
